datacore/__about__.py
datacore/__init__.py
datacore-0.0.1.dist-info/METADATA
datacore-0.0.1.dist-info/WHEEL
datacore-0.0.1.dist-info/licenses/LICENSE.txt
datacore-0.0.1.dist-info/RECORD
